pycheval/__init__.py
pycheval/_locale.py
pycheval/_test_data.py
pycheval/const.py
pycheval/countries.py
pycheval/exc.py
pycheval/format.py
pycheval/generate.py
pycheval/locale/de/LC_MESSAGES/pycheval.mo
pycheval/locale/de/LC_MESSAGES/pycheval.po
pycheval/model.py
pycheval/money.py
pycheval/parse.py
pycheval/pdf_common.py
pycheval/pdf_embed.py
pycheval/pdf_extract.py
pycheval/pdf_parse.py
pycheval/py.typed
pycheval/quantities.py
pycheval/type_codes.py
pycheval/types.py
pycheval-0.3.0.dist-info/METADATA
pycheval-0.3.0.dist-info/WHEEL
pycheval-0.3.0.dist-info/licenses/LICENSE
pycheval-0.3.0.dist-info/RECORD
