Metadata-Version: 2.4
Name: PyCheval
Version: 0.3.0
Summary: Factur-X/ZUGFeRD parsing and generation library for Python
License-Expression: Apache-2.0
License-File: LICENSE
Keywords: factur-x,zugferd,invoice,billing
Author: Sebastian Rittau
Author-email: sebastian.rittau@zfutura.de
Requires-Python: >= 3.11
Classifier: Development Status :: 3 - Alpha
Classifier: Intended Audience :: Developers
Classifier: Topic :: File Formats
Classifier: Topic :: Office/Business :: Financial :: Accounting
Requires-Dist: pypdf (>=6.1.1,<7)
Project-URL: GitHub, https://github.com/zfutura/pycheval
